{"data": [{"author": "ohp-thatslife", "author_flair_css_class": null, "author_flair_richtext": [], "author_flair_text": null, "author_flair_type": "text", "author_fullname": "t2_2jjhp9hj", "author_patreon_flair": false, "can_mod_post": false, "contest_mode": false, "created_utc": 1541404062, "domain": "self.cripplingalcoholism", "full_link": "https://www.reddit.com/r/cripplingalcoholism/comments/9ubnvv/after_a_year_sober_started_drinking_again_to/", "gildings": {"gid_1": 0, "gid_2": 0, "gid_3": 0}, "id": "9ubnvv", "is_crosspostable": false, "is_meta": false, "is_original_content": false, "is_reddit_media_domain": false, "is_robot_indexable": false, "is_self": true, "is_video": false, "link_flair_background_color": "", "link_flair_richtext": [], "link_flair_text_color": "dark", "link_flair_type": "text", "locked": false, "media_only": false, "no_follow": true, "num_comments": 0, "num_crossposts": 0, "over_18": false, "parent_whitelist_status": "house_only", "permalink": "/r/cripplingalcoholism/comments/9ubnvv/after_a_year_sober_started_drinking_again_to/", "pinned": false, "pwls": 1, "retrieved_on": 1541404063, "score": 1, "selftext": "[removed]", "send_replies": true, "spoiler": false, "stickied": false, "subreddit": "cripplingalcoholism", "subreddit_id": "t5_2s68b", "subreddit_subscribers": 32823, "subreddit_type": "public", "thumbnail": "self", "title": "After a year sober, started drinking again to prove I could control myself, and in two months I\u2019m right back where I started", "url": "https://www.reddit.com/r/cripplingalcoholism/comments/9ubnvv/after_a_year_sober_started_drinking_again_to/", "whitelist_status": "house_only", "wls": 1}, {"author": "ohp-thatslife", "author_flair_css_class": null, "author_flair_richtext": [], "author_flair_text": null, "author_flair_type": "text", "author_fullname": "t2_2jjhp9hj", "author_patreon_flair": false, "can_mod_post": false, "contest_mode": false, "created_utc": 1541401409, "domain": "self.depression", "full_link": "https://www.reddit.com/r/depression/comments/9ubfyv/oscillating_between_happy_and_sad_cant_remember/", "gildings": {"gid_1": 0, "gid_2": 0, "gid_3": 0}, "id": "9ubfyv", "is_crosspostable": true, "is_meta": false, "is_original_content": false, "is_reddit_media_domain": false, "is_robot_indexable": true, "is_self": true, "is_video": false, "link_flair_background_color": "", "link_flair_richtext": [], "link_flair_text_color": "dark", "link_flair_type": "text", "locked": false, "media_only": false, "no_follow": true, "num_comments": 3, "num_crossposts": 0, "over_18": false, "parent_whitelist_status": "no_ads", "permalink": "/r/depression/comments/9ubfyv/oscillating_between_happy_and_sad_cant_remember/", "pinned": false, "pwls": 0, "retrieved_on": 1541401410, "score": 1, "selftext": "I was diagnosed with seasonal affective disorder at 16, which eventually progressed into the premium year round version. Sometimes I\u2019m happy for stretches of time, and sometimes I\u2019m really depressed and suicidal out of the blue. Problem is, when I\u2019m happy I can\u2019t remember feeling sad. I know objectively I must\u2019ve been sad because I remember laying in bed for days staring at the wall and crying. But I can\u2019t remember the feeling, and consequently, tend to dismiss the previous episode as me just being irrational or not getting enough sleep, and totally manageable if I wasn\u2019t such a lazy pos.\nOn the flip side, when I\u2019m depressed, I can\u2019t remember the feeling of happiness. And it feels like it\u2019ll never be possible to feel happiness ever again. Sometimes these swings even happen within the same day.\nI am a completely different person from one extreme to the other. It\u2019s not just acting different, I just don\u2019t even identify with my other self. I have to read through texts and notes and try to piece together why my other self acted the way she did. Sometimes \nDoes anyone else experience this? It\u2019s only getting worse year to year and I know I need to get help, but it\u2019s really hard to convince my happy self to get help when it doesn\u2019t seem like a big deal or a problem, and it\u2019s hard to motivate my depressed self to even get out of bed. ", "send_replies": true, "spoiler": false, "stickied": false, "subreddit": "depression", "subreddit_id": "t5_2qqqf", "subreddit_subscribers": 402558, "subreddit_type": "public", "suggested_sort": "confidence", "thumbnail": "self", "title": "Oscillating between happy and sad, can\u2019t remember either. I feel like two different people - is this normal?", "url": "https://www.reddit.com/r/depression/comments/9ubfyv/oscillating_between_happy_and_sad_cant_remember/", "whitelist_status": "no_ads", "wls": 0}]}