{"data": [{"author": "zzzzkhi", "author_flair_css_class": null, "author_flair_richtext": [], "author_flair_text": null, "author_flair_type": "text", "author_fullname": "t2_1k1bfsqq", "author_patreon_flair": false, "can_mod_post": false, "contest_mode": false, "created_utc": 1542246198, "domain": "self.depression", "full_link": "https://www.reddit.com/r/depression/comments/9x6jcd/university_vent/", "gildings": {"gid_1": 0, "gid_2": 0, "gid_3": 0}, "id": "9x6jcd", "is_crosspostable": true, "is_meta": false, "is_original_content": false, "is_reddit_media_domain": false, "is_robot_indexable": true, "is_self": true, "is_video": false, "link_flair_background_color": "", "link_flair_richtext": [], "link_flair_text_color": "dark", "link_flair_type": "text", "locked": false, "media_only": false, "no_follow": true, "num_comments": 2, "num_crossposts": 0, "over_18": false, "parent_whitelist_status": "no_ads", "permalink": "/r/depression/comments/9x6jcd/university_vent/", "pinned": false, "pwls": 0, "retrieved_on": 1542246200, "score": 1, "selftext": "I don't know how long I've been depressed but was diagnosed with chronic depression (at the time I'm fairly functional and drag myself to the hospital  but  I've had  weeks  long  of  being  shut  ins) but honestly I've been trying to do better. I'm 5 years in college now I'm 20, I really need to graduate next year, but last week when I finally put my graduation paper submission in the lady said I need to wait at least a month.\n\nI'm so infuriated by myself of how I let my social anxiety and depression gets past me, I spend 1 year or more just being scared of the prospect of talking to the teachers / professors and the front offices.\n\nI'm tired and don't know how to strive for the better, the joke is my studies is far from over. Even if I graduate bachelor degree, I need to do clinical rotation and internship for 3 years minimal before finally able to get a job in my field.\n\nI can't quit, I can't afford to quit but continuing this path seems hard. I love drawing more than my own major, but I realized it too late, I use it as escapism. I'm not suicidal but fuck I had thoughts how much easier it would be for my parents if I were not here at all.", "send_replies": true, "spoiler": false, "stickied": false, "subreddit": "depression", "subreddit_id": "t5_2qqqf", "subreddit_subscribers": 405834, "subreddit_type": "public", "suggested_sort": "confidence", "thumbnail": "self", "title": "university vent", "url": "https://www.reddit.com/r/depression/comments/9x6jcd/university_vent/", "whitelist_status": "no_ads", "wls": 0}, {"author": "zzzzkhi", "author_flair_css_class": null, "author_flair_richtext": [], "author_flair_text": null, "author_flair_type": "text", "author_fullname": "t2_1k1bfsqq", "author_patreon_flair": false, "can_mod_post": false, "contest_mode": false, "created_utc": 1542243949, "domain": "self.depression", "full_link": "https://www.reddit.com/r/depression/comments/9x68t0/college_vent/", "gildings": {"gid_1": 0, "gid_2": 0, "gid_3": 0}, "id": "9x68t0", "is_crosspostable": true, "is_meta": false, "is_original_content": false, "is_reddit_media_domain": false, "is_robot_indexable": true, "is_self": true, "is_video": false, "link_flair_background_color": "", "link_flair_richtext": [], "link_flair_text_color": "dark", "link_flair_type": "text", "locked": false, "media_only": false, "no_follow": true, "num_comments": 0, "num_crossposts": 0, "over_18": false, "parent_whitelist_status": "no_ads", "permalink": "/r/depression/comments/9x68t0/college_vent/", "pinned": false, "pwls": 0, "retrieved_on": 1542243950, "score": 1, "selftext": "I just wanna rant for a bit, I'm in college. Fair enough people in university are depressed. Yada  yada, I  know  I'm not  special. I'm tired  being  told  everyone are  depressed, no  shit.\n\nBut I spend more than a year agonizing over my graduation paper title, over the social anxiety having to talk with the professors / teachers, writing out proposals without thinking straight. And last week I finally submitted my long dreaded fear of a title to the academic offices and the lady there said I've to wait a month before I knew whether or not it would get approved.\n\nI'm just,, what if it doesn't get approved, do I just wait for another month to submit a title. I'm 5 years in college now, I'm just fucking done I hate being cripplingly depressed and anxious. I'm not suicidal but fuck I hate not being able to open up and don't have any support system. I truly fucked up.\n", "send_replies": true, "spoiler": false, "stickied": false, "subreddit": "depression", "subreddit_id": "t5_2qqqf", "subreddit_subscribers": 405824, "subreddit_type": "public", "suggested_sort": "confidence", "thumbnail": "self", "title": "College vent", "url": "https://www.reddit.com/r/depression/comments/9x68t0/college_vent/", "whitelist_status": "no_ads", "wls": 0}, {"author": "zzzzkhi", "author_flair_css_class": null, "author_flair_richtext": [], "author_flair_text": null, "author_flair_type": "text", "author_fullname": "t2_1k1bfsqq", "author_patreon_flair": false, "can_mod_post": false, "contest_mode": false, "created_utc": 1542124834, "domain": "self.socialanxiety", "full_link": "https://www.reddit.com/r/socialanxiety/comments/9wq9sl/front_office_fear/", "gildings": {"gid_1": 0, "gid_2": 0, "gid_3": 0}, "id": "9wq9sl", "is_crosspostable": true, "is_meta": false, "is_original_content": false, "is_reddit_media_domain": false, "is_robot_indexable": true, "is_self": true, "is_video": false, "link_flair_background_color": "", "link_flair_richtext": [], "link_flair_text_color": "dark", "link_flair_type": "text", "locked": false, "media_only": false, "no_follow": true, "num_comments": 1, "num_crossposts": 0, "over_18": false, "parent_whitelist_status": "all_ads", "permalink": "/r/socialanxiety/comments/9wq9sl/front_office_fear/", "pinned": false, "pwls": 6, "retrieved_on": 1542124835, "score": 1, "selftext": "I don't know what it is but I'm just scared of talking to front offices in my university, I don't have physical reaction / panic attacks but I feel like I'm wasting their time by talking.\n\nI don't have the same issue with most public places though (ex: cashier, bank tellers)\nIs this normal?", "send_replies": true, "spoiler": false, "stickied": false, "subreddit": "socialanxiety", "subreddit_id": "t5_2r22n", "subreddit_subscribers": 129726, "subreddit_type": "public", "thumbnail": "self", "title": "front office fear", "url": "https://www.reddit.com/r/socialanxiety/comments/9wq9sl/front_office_fear/", "whitelist_status": "all_ads", "wls": 6}, {"author": "zzzzkhi", "author_flair_css_class": null, "author_flair_richtext": [], "author_flair_text": null, "author_flair_type": "text", "author_fullname": "t2_1k1bfsqq", "author_patreon_flair": false, "can_mod_post": false, "contest_mode": false, "created_utc": 1542009124, "domain": "self.depression", "full_link": "https://www.reddit.com/r/depression/comments/9wc35i/apathy_since_childhood/", "gildings": {"gid_1": 0, "gid_2": 0, "gid_3": 0}, "id": "9wc35i", "is_crosspostable": true, "is_meta": false, "is_original_content": false, "is_reddit_media_domain": false, "is_robot_indexable": true, "is_self": true, "is_video": false, "link_flair_background_color": "", "link_flair_richtext": [], "link_flair_text_color": "dark", "link_flair_type": "text", "locked": false, "media_only": false, "no_follow": true, "num_comments": 2, "num_crossposts": 0, "over_18": false, "parent_whitelist_status": "no_ads", "permalink": "/r/depression/comments/9wc35i/apathy_since_childhood/", "pinned": false, "pwls": 0, "retrieved_on": 1542009126, "score": 1, "selftext": "I don't know if what I have is caused purely based on brain chemical abnormality or situational, since my life is objectively shitty since I don't really have things that I achieved on my own/being proud of. But in retrospect I've been pretty apathetic towards anything in life. I remember jokingly said about suicide and I still can't fathom how did I even thought about it as a kid  (jokingly  said  it  to  my  mom) .. ", "send_replies": true, "spoiler": false, "stickied": false, "subreddit": "depression", "subreddit_id": "t5_2qqqf", "subreddit_subscribers": 404822, "subreddit_type": "public", "suggested_sort": "confidence", "thumbnail": "self", "title": "Apathy since Childhood", "url": "https://www.reddit.com/r/depression/comments/9wc35i/apathy_since_childhood/", "whitelist_status": "no_ads", "wls": 0}, {"author": "zzzzkhi", "author_flair_css_class": null, "author_flair_richtext": [], "author_flair_text": null, "author_flair_type": "text", "author_fullname": "t2_1k1bfsqq", "author_patreon_flair": false, "can_mod_post": false, "contest_mode": false, "created_utc": 1541946765, "domain": "self.depression", "full_link": "https://www.reddit.com/r/depression/comments/9w470a/i_did_my_dishes_two_days_ago_and_back_to/", "gildings": {"gid_1": 0, "gid_2": 0, "gid_3": 0}, "id": "9w470a", "is_crosspostable": true, "is_meta": false, "is_original_content": false, "is_reddit_media_domain": false, "is_robot_indexable": true, "is_self": true, "is_video": false, "link_flair_background_color": "", "link_flair_richtext": [], "link_flair_text_color": "dark", "link_flair_type": "text", "locked": false, "media_only": false, "no_follow": true, "num_comments": 0, "num_crossposts": 0, "over_18": false, "parent_whitelist_status": "no_ads", "permalink": "/r/depression/comments/9w470a/i_did_my_dishes_two_days_ago_and_back_to/", "pinned": false, "pwls": 0, "retrieved_on": 1541946765, "score": 1, "selftext": "Vent- \n\nI know it's hard to change habits, god I've been trying since last year, to at least care more.. About myself, my surrounding, my life. Apathy has rooted deep in my mind. I've laid in bed for the whole day yesterday and today.\n\nI'm not on med rn and I've been thinking maybe going back would help but no one in my family is supportive of me to take meds. ", "send_replies": true, "spoiler": false, "stickied": false, "subreddit": "depression", "subreddit_id": "t5_2qqqf", "subreddit_subscribers": 404439, "subreddit_type": "public", "suggested_sort": "confidence", "thumbnail": "self", "title": "I did my dishes two days ago and back to depression mode right after", "url": "https://www.reddit.com/r/depression/comments/9w470a/i_did_my_dishes_two_days_ago_and_back_to/", "whitelist_status": "no_ads", "wls": 0}, {"author": "zzzzkhi", "author_flair_css_class": null, "author_flair_richtext": [], "author_flair_text": null, "author_flair_type": "text", "author_fullname": "t2_1k1bfsqq", "author_patreon_flair": false, "can_mod_post": false, "contest_mode": false, "created_utc": 1541748022, "domain": "self.depression", "full_link": "https://www.reddit.com/r/depression/comments/9vifq8/washed_2_weeks_worth_of_dishes_last_night/", "gildings": {"gid_1": 0, "gid_2": 0, "gid_3": 0}, "id": "9vifq8", "is_crosspostable": true, "is_meta": false, "is_original_content": false, "is_reddit_media_domain": false, "is_robot_indexable": true, "is_self": true, "is_video": false, "link_flair_background_color": "", "link_flair_richtext": [], "link_flair_text_color": "dark", "link_flair_type": "text", "locked": false, "media_only": false, "no_follow": true, "num_comments": 2, "num_crossposts": 0, "over_18": false, "parent_whitelist_status": "no_ads", "permalink": "/r/depression/comments/9vifq8/washed_2_weeks_worth_of_dishes_last_night/", "pinned": false, "pwls": 0, "retrieved_on": 1541748022, "score": 1, "selftext": "stayed up til 2-3am because I cant sleep.\nIt's prolly  something small  but  at  least  I  did  it. I'm honestly just never thought how therapeutic it's to dedicate a time for cleaning. Next is my room and laundry.\n\nI hate when I had my down weeks for the past two weeks, it's really hard to even care. Not being productive and failing college shit, I ve been a human garbage for my life. I need to get this together.. I'm sick feeling like I cant even walk on my own foot. ", "send_replies": true, "spoiler": false, "stickied": false, "subreddit": "depression", "subreddit_id": "t5_2qqqf", "subreddit_subscribers": 403633, "subreddit_type": "public", "suggested_sort": "confidence", "thumbnail": "self", "title": "washed 2 weeks worth of dishes last night", "url": "https://www.reddit.com/r/depression/comments/9vifq8/washed_2_weeks_worth_of_dishes_last_night/", "whitelist_status": "no_ads", "wls": 0}, {"author": "zzzzkhi", "author_flair_css_class": null, "author_flair_richtext": [], "author_flair_text": null, "author_flair_type": "text", "author_fullname": "t2_1k1bfsqq", "author_patreon_flair": false, "can_mod_post": false, "contest_mode": false, "created_utc": 1541687636, "domain": "self.depression", "full_link": "https://www.reddit.com/r/depression/comments/9vahdz/should_i_take_anti_depressant/", "gildings": {"gid_1": 0, "gid_2": 0, "gid_3": 0}, "id": "9vahdz", "is_crosspostable": true, "is_meta": false, "is_original_content": false, "is_reddit_media_domain": false, "is_robot_indexable": true, "is_self": true, "is_video": false, "link_flair_background_color": "", "link_flair_richtext": [], "link_flair_text_color": "dark", "link_flair_type": "text", "locked": false, "media_only": false, "no_follow": true, "num_comments": 3, "num_crossposts": 0, "over_18": false, "parent_whitelist_status": "no_ads", "permalink": "/r/depression/comments/9vahdz/should_i_take_anti_depressant/", "pinned": false, "pwls": 0, "retrieved_on": 1541687637, "score": 1, "selftext": "I've only been on for 4 weeks on prozac (first line for depression in my country) but I noticed it made me so sleepy and induced more insomnia in the beginning. It's been 2-3 months still I get anti depressant again, I still have relapse on one week of can't do anything productive, mental breakdown and occasional suicidal thoughts (I'm not suicidal tho but I believe no matter what I do my future will always be bleak.).\n\nI drink a lot of coffee today (I'm not a regular /addicted to caffeine) but it felt good; like agitated, maybe bit antsy. I wonder if caffeine is a good way to cope or should I get back to therapy?", "send_replies": true, "spoiler": false, "stickied": false, "subreddit": "depression", "subreddit_id": "t5_2qqqf", "subreddit_subscribers": 403420, "subreddit_type": "public", "suggested_sort": "confidence", "thumbnail": "self", "title": "Should i take anti depressant?", "url": "https://www.reddit.com/r/depression/comments/9vahdz/should_i_take_anti_depressant/", "whitelist_status": "no_ads", "wls": 0}, {"author": "zzzzkhi", "author_flair_css_class": null, "author_flair_richtext": [], "author_flair_text": null, "author_flair_type": "text", "author_fullname": "t2_1k1bfsqq", "author_patreon_flair": false, "can_mod_post": false, "contest_mode": false, "created_utc": 1541576560, "domain": "self.depression", "full_link": "https://www.reddit.com/r/depression/comments/9uxg7k/the_future_is_bleak_despite_being_in_higher/", "gildings": {"gid_1": 0, "gid_2": 0, "gid_3": 0}, "id": "9uxg7k", "is_crosspostable": true, "is_meta": false, "is_original_content": false, "is_reddit_media_domain": false, "is_robot_indexable": true, "is_self": true, "is_video": false, "link_flair_background_color": "", "link_flair_richtext": [], "link_flair_text_color": "dark", "link_flair_type": "text", "locked": false, "media_only": false, "no_follow": true, "num_comments": 0, "num_crossposts": 0, "over_18": false, "parent_whitelist_status": "no_ads", "permalink": "/r/depression/comments/9uxg7k/the_future_is_bleak_despite_being_in_higher/", "pinned": false, "pwls": 0, "retrieved_on": 1541576560, "score": 1, "selftext": "I know thinking that anything is futile is a sign of depression but I just think even if I managed to graduate somehow even really late, I won't have a great job. I still be lonely and friend less. Nothing would change and probably will still be depressed at 25 and so on.\n\nThey say just go to a good college, but it's just made me worse and it worsened my life because I'm not that stable in the first place. Sure I won't be seen jumping from a building, but even being functional is hard.", "send_replies": true, "spoiler": false, "stickied": false, "subreddit": "depression", "subreddit_id": "t5_2qqqf", "subreddit_subscribers": 403098, "subreddit_type": "public", "suggested_sort": "confidence", "thumbnail": "self", "title": "The future is bleak despite being in higher education", "url": "https://www.reddit.com/r/depression/comments/9uxg7k/the_future_is_bleak_despite_being_in_higher/", "whitelist_status": "no_ads", "wls": 0}, {"author": "zzzzkhi", "author_flair_css_class": null, "author_flair_richtext": [], "author_flair_text": null, "author_flair_type": "text", "author_fullname": "t2_1k1bfsqq", "author_patreon_flair": false, "can_mod_post": false, "contest_mode": false, "created_utc": 1541576151, "domain": "self.depression", "full_link": "https://www.reddit.com/r/depression/comments/9uxetq/having_a_hard_time_to_go_out/", "gildings": {"gid_1": 0, "gid_2": 0, "gid_3": 0}, "id": "9uxetq", "is_crosspostable": true, "is_meta": false, "is_original_content": false, "is_reddit_media_domain": false, "is_robot_indexable": true, "is_self": true, "is_video": false, "link_flair_background_color": "", "link_flair_richtext": [], "link_flair_text_color": "dark", "link_flair_type": "text", "locked": false, "media_only": false, "no_follow": true, "num_comments": 3, "num_crossposts": 0, "over_18": false, "parent_whitelist_status": "no_ads", "permalink": "/r/depression/comments/9uxetq/having_a_hard_time_to_go_out/", "pinned": false, "pwls": 0, "retrieved_on": 1541576152, "score": 1, "selftext": "I'm relapsing to depression episode I think, it's been a week and I haven't go out and do anything worthwhile at all. My cat left me too, idk where. I wish I could rot but death somewhat scared me.", "send_replies": true, "spoiler": false, "stickied": false, "subreddit": "depression", "subreddit_id": "t5_2qqqf", "subreddit_subscribers": 403095, "subreddit_type": "public", "suggested_sort": "confidence", "thumbnail": "self", "title": "Having a hard time to go out", "url": "https://www.reddit.com/r/depression/comments/9uxetq/having_a_hard_time_to_go_out/", "whitelist_status": "no_ads", "wls": 0}, {"author": "zzzzkhi", "author_flair_css_class": null, "author_flair_richtext": [], "author_flair_text": null, "author_flair_type": "text", "author_fullname": "t2_1k1bfsqq", "author_patreon_flair": false, "can_mod_post": false, "contest_mode": false, "created_utc": 1541529687, "domain": "self.depression", "full_link": "https://www.reddit.com/r/depression/comments/9ur1si/its_just_depression_right/", "gildings": {"gid_1": 0, "gid_2": 0, "gid_3": 0}, "id": "9ur1si", "is_crosspostable": true, "is_meta": false, "is_original_content": false, "is_reddit_media_domain": false, "is_robot_indexable": true, "is_self": true, "is_video": false, "link_flair_background_color": "", "link_flair_richtext": [], "link_flair_text_color": "dark", "link_flair_type": "text", "locked": false, "media_only": false, "no_follow": true, "num_comments": 0, "num_crossposts": 0, "over_18": false, "parent_whitelist_status": "no_ads", "permalink": "/r/depression/comments/9ur1si/its_just_depression_right/", "pinned": false, "pwls": 0, "retrieved_on": 1541529688, "score": 1, "selftext": "I remember my older sibling coming home asking me this, yeah I don't have bipolar, personality disorder etc etc  it's just  depression\n\nmaybe it looks normal because I pretend to be in front of you.\n\nMaybe you didn't mean anything bad by asking and phrasing it that way. When you're gone of course I'm an absolute mess again, I don't know why I'm like this either fuck me", "send_replies": true, "spoiler": false, "stickied": false, "subreddit": "depression", "subreddit_id": "t5_2qqqf", "subreddit_subscribers": 402965, "subreddit_type": "public", "suggested_sort": "confidence", "thumbnail": "self", "title": "\"It's just depression right?\"", "url": "https://www.reddit.com/r/depression/comments/9ur1si/its_just_depression_right/", "whitelist_status": "no_ads", "wls": 0}, {"author": "zzzzkhi", "author_flair_css_class": null, "author_flair_richtext": [], "author_flair_text": null, "author_flair_type": "text", "author_fullname": "t2_1k1bfsqq", "author_patreon_flair": false, "can_mod_post": false, "contest_mode": false, "created_utc": 1541401088, "domain": "self.CPTSD", "full_link": "https://www.reddit.com/r/CPTSD/comments/9ubevt/why_its_so_hard_to_open_up_to_my_parents/", "gildings": {"gid_1": 0, "gid_2": 0, "gid_3": 0}, "id": "9ubevt", "is_crosspostable": true, "is_meta": false, "is_original_content": false, "is_reddit_media_domain": false, "is_robot_indexable": true, "is_self": true, "is_video": false, "link_flair_background_color": "", "link_flair_richtext": [], "link_flair_text_color": "dark", "link_flair_type": "text", "locked": false, "media_only": false, "no_follow": true, "num_comments": 6, "num_crossposts": 0, "over_18": false, "parent_whitelist_status": "no_ads", "permalink": "/r/CPTSD/comments/9ubevt/why_its_so_hard_to_open_up_to_my_parents/", "pinned": false, "pwls": 0, "retrieved_on": 1541401089, "score": 1, "selftext": "When they had good intention, I was emotionally neglected, never been physically abused by them but I feel my dad is actually making efforts to call me often, but I just feel like I'm pretending whenever I'm talking to them. No matter how much of a good will people shows, I cant help but distrust them.", "send_replies": true, "spoiler": false, "stickied": false, "subreddit": "CPTSD", "subreddit_id": "t5_2vvid", "subreddit_subscribers": 16372, "subreddit_type": "public", "thumbnail": "self", "title": "Why it's so hard to open up to my parents?", "url": "https://www.reddit.com/r/CPTSD/comments/9ubevt/why_its_so_hard_to_open_up_to_my_parents/", "whitelist_status": "no_ads", "wls": 0}, {"author": "zzzzkhi", "author_flair_css_class": null, "author_flair_richtext": [], "author_flair_text": null, "author_flair_type": "text", "author_fullname": "t2_1k1bfsqq", "author_patreon_flair": false, "can_mod_post": false, "contest_mode": false, "created_utc": 1541357088, "domain": "self.Trufemcels", "full_link": "https://www.reddit.com/r/Trufemcels/comments/9u5vsy/whats_the_one_feature_you_like_about_your_face/", "gildings": {"gid_1": 0, "gid_2": 0, "gid_3": 0}, "id": "9u5vsy", "is_crosspostable": false, "is_meta": false, "is_original_content": false, "is_reddit_media_domain": false, "is_robot_indexable": false, "is_self": true, "is_video": false, "link_flair_background_color": "", "link_flair_richtext": [], "link_flair_text_color": "dark", "link_flair_type": "text", "locked": false, "media_only": false, "no_follow": true, "num_comments": 20, "num_crossposts": 0, "over_18": false, "permalink": "/r/Trufemcels/comments/9u5vsy/whats_the_one_feature_you_like_about_your_face/", "pinned": false, "retrieved_on": 1541357089, "score": 1, "selftext": "[removed]", "send_replies": true, "spoiler": false, "stickied": false, "subreddit": "Trufemcels", "subreddit_id": "t5_hnz41", "subreddit_subscribers": 5671, "subreddit_type": "public", "thumbnail": "self", "title": "What's the one feature you like about your face?", "url": "https://www.reddit.com/r/Trufemcels/comments/9u5vsy/whats_the_one_feature_you_like_about_your_face/"}, {"author": "zzzzkhi", "author_flair_css_class": null, "author_flair_richtext": [], "author_flair_text": null, "author_flair_type": "text", "author_fullname": "t2_1k1bfsqq", "author_patreon_flair": false, "can_mod_post": false, "contest_mode": false, "created_utc": 1541342731, "domain": "self.CPTSD", "full_link": "https://www.reddit.com/r/CPTSD/comments/9u3ufg/was_this_a_flashback/", "gildings": {"gid_1": 0, "gid_2": 0, "gid_3": 0}, "id": "9u3ufg", "is_crosspostable": true, "is_meta": false, "is_original_content": false, "is_reddit_media_domain": false, "is_robot_indexable": true, "is_self": true, "is_video": false, "link_flair_background_color": "", "link_flair_richtext": [], "link_flair_text_color": "dark", "link_flair_type": "text", "locked": false, "media_only": false, "no_follow": true, "num_comments": 0, "num_crossposts": 0, "over_18": false, "parent_whitelist_status": "no_ads", "permalink": "/r/CPTSD/comments/9u3ufg/was_this_a_flashback/", "pinned": false, "pwls": 0, "retrieved_on": 1541342732, "score": 1, "selftext": "I never been physically abused, but after reading about it I believe was emotionally neglected by my parents. I'm now 20, but this particular event happened maybe when I was 15-16? I was entering uni while my sister is graduating and for I cried. Not because I'll miss her, I can't exactly pin point why and it got my dad annoyed at me for ruining the thing.\n\nI thought maybe it's just a teen angst and years later I still had this thing except worse because now I don't function properly in a day to day basis. I'm graduating 2 years late because of depression, and had this thing where I suddenly for no reason felt really bad. My family told me to not take AD and therapy session and of course I complied with them, I don't feel supported even though my dad tried to call me everyday. I feel like even around them I'm forced to pretend I'm okay, I don't want to blame them because inevitably every actions was my own fault.", "send_replies": true, "spoiler": false, "stickied": false, "subreddit": "CPTSD", "subreddit_id": "t5_2vvid", "subreddit_subscribers": 16309, "subreddit_type": "public", "thumbnail": "self", "title": "Was this a flashback?", "url": "https://www.reddit.com/r/CPTSD/comments/9u3ufg/was_this_a_flashback/", "whitelist_status": "no_ads", "wls": 0}, {"author": "zzzzkhi", "author_flair_css_class": null, "author_flair_richtext": [], "author_flair_text": null, "author_flair_type": "text", "author_fullname": "t2_1k1bfsqq", "author_patreon_flair": false, "can_mod_post": false, "contest_mode": false, "created_utc": 1541243218, "domain": "i.redd.it", "full_link": "https://www.reddit.com/r/Trufemcels/comments/9tt959/pink_pill_from_a_comic_i_recently_read/", "gildings": {"gid_1": 0, "gid_2": 0, "gid_3": 0}, "id": "9tt959", "is_crosspostable": true, "is_meta": false, "is_original_content": false, "is_reddit_media_domain": true, "is_robot_indexable": true, "is_self": false, "is_video": false, "link_flair_background_color": "", "link_flair_richtext": [], "link_flair_text_color": "dark", "link_flair_type": "text", "locked": false, "media_only": false, "no_follow": true, "num_comments": 6, "num_crossposts": 0, "over_18": false, "permalink": "/r/Trufemcels/comments/9tt959/pink_pill_from_a_comic_i_recently_read/", "pinned": false, "retrieved_on": 1541243218, "score": 1, "selftext": "", "send_replies": true, "spoiler": false, "stickied": false, "subreddit": "Trufemcels", "subreddit_id": "t5_hnz41", "subreddit_subscribers": 5583, "subreddit_type": "public", "thumbnail": "default", "title": "pink pill from a comic i recently read", "url": "https://i.redd.it/md90qj2vl3w11.jpg"}, {"author": "zzzzkhi", "author_flair_css_class": null, "author_flair_richtext": [], "author_flair_text": null, "author_flair_type": "text", "author_fullname": "t2_1k1bfsqq", "author_patreon_flair": false, "can_mod_post": false, "contest_mode": false, "created_utc": 1541242790, "domain": "i.redd.it", "full_link": "https://www.reddit.com/r/Trufemcels/comments/9tt7u6/from_sensei_no_shiroi_uso/", "gildings": {"gid_1": 0, "gid_2": 0, "gid_3": 0}, "id": "9tt7u6", "is_crosspostable": true, "is_meta": false, "is_original_content": false, "is_reddit_media_domain": true, "is_robot_indexable": true, "is_self": false, "is_video": false, "link_flair_background_color": "", "link_flair_richtext": [], "link_flair_text_color": "dark", "link_flair_type": "text", "locked": false, "media_only": false, "no_follow": true, "num_comments": 0, "num_crossposts": 0, "over_18": false, "permalink": "/r/Trufemcels/comments/9tt7u6/from_sensei_no_shiroi_uso/", "pinned": false, "post_hint": "image", "preview": {"enabled": true, "images": [{"id": "x6boeVj9k8oPB1X_4U06Of95UhYre6LHA6e2RF9elp8", "resolutions": [{"height": 154, "url": "https://preview.redd.it/ydzvylelk3w11.jpg?width=108&amp;crop=smart&amp;auto=webp&amp;s=311e32f4d4246dc8034d1c68a0549d062a646c63", "width": 108}, {"height": 308, "url": "https://preview.redd.it/ydzvylelk3w11.jpg?width=216&amp;crop=smart&amp;auto=webp&amp;s=4c8083388a28103acb67cab7da63e389b3e31314", "width": 216}, {"height": 457, "url": "https://preview.redd.it/ydzvylelk3w11.jpg?width=320&amp;crop=smart&amp;auto=webp&amp;s=3cc825ab7b55b4259b8e0aa072562af28e95dc53", "width": 320}, {"height": 914, "url": "https://preview.redd.it/ydzvylelk3w11.jpg?width=640&amp;crop=smart&amp;auto=webp&amp;s=118a637ebffb69f35b789c865d54eb6eccf86f48", "width": 640}], "source": {"height": 1242, "url": "https://preview.redd.it/ydzvylelk3w11.jpg?auto=webp&amp;s=73d3516de6643e34dd5f4d1223d180630b5da332", "width": 869}, "variants": {}}]}, "retrieved_on": 1541242792, "score": 1, "selftext": "", "send_replies": true, "spoiler": false, "stickied": false, "subreddit": "Trufemcels", "subreddit_id": "t5_hnz41", "subreddit_subscribers": 5583, "subreddit_type": "public", "thumbnail": "https://b.thumbs.redditmedia.com/Xyw4MoQ5Ov8a7HojIiNYoqACiMEmmeSxM0GcN6TBxwI.jpg", "thumbnail_height": 140, "thumbnail_width": 140, "title": "From Sensei no Shiroi Uso", "url": "https://i.redd.it/ydzvylelk3w11.jpg"}, {"author": "zzzzkhi", "author_flair_css_class": null, "author_flair_richtext": [], "author_flair_text": null, "author_flair_type": "text", "author_fullname": "t2_1k1bfsqq", "author_patreon_flair": false, "can_mod_post": false, "contest_mode": false, "created_utc": 1541151792, "domain": "self.CPTSD", "full_link": "https://www.reddit.com/r/CPTSD/comments/9tikht/trust_issues/", "gildings": {"gid_1": 0, "gid_2": 0, "gid_3": 0}, "id": "9tikht", "is_crosspostable": true, "is_meta": false, "is_original_content": false, "is_reddit_media_domain": false, "is_robot_indexable": true, "is_self": true, "is_video": false, "link_flair_background_color": "", "link_flair_richtext": [], "link_flair_text_color": "dark", "link_flair_type": "text", "locked": false, "media_only": false, "no_follow": true, "num_comments": 2, "num_crossposts": 0, "over_18": false, "parent_whitelist_status": "no_ads", "permalink": "/r/CPTSD/comments/9tikht/trust_issues/", "pinned": false, "pwls": 0, "retrieved_on": 1541151793, "score": 1, "selftext": "Sort of a vent post; heads up, I don't know if I have cptsd but I do somewhat realize I've had been emotionally neglected.\n\nMaybe what make it worse and made me fall into clinical depression is that how when I was bullied in middle school and high school, I never bothered to tell it to anyone. Not my friends, not my parents not teacher. Perhaps part of me just accepted it's normal to be treated this way, that I don't deserve to be better. I was functional until recently, I hardly ever left the house. I hate waking up or doing anything when my mom is around, I feel like a failure. I wish I could off myself without even existing in the first place.", "send_replies": true, "spoiler": false, "stickied": false, "subreddit": "CPTSD", "subreddit_id": "t5_2vvid", "subreddit_subscribers": 16092, "subreddit_type": "public", "thumbnail": "self", "title": "Trust issues", "url": "https://www.reddit.com/r/CPTSD/comments/9tikht/trust_issues/", "whitelist_status": "no_ads", "wls": 0}, {"author": "zzzzkhi", "author_flair_css_class": null, "author_flair_richtext": [], "author_flair_text": null, "author_flair_type": "text", "author_fullname": "t2_1k1bfsqq", "author_patreon_flair": false, "can_mod_post": false, "contest_mode": false, "created_utc": 1540884866, "domain": "self.depression", "full_link": "https://www.reddit.com/r/depression/comments/9slpyz/feels_like_a_fake/", "gildings": {"gid_1": 0, "gid_2": 0, "gid_3": 0}, "id": "9slpyz", "is_crosspostable": true, "is_meta": false, "is_original_content": false, "is_reddit_media_domain": false, "is_robot_indexable": true, "is_self": true, "is_video": false, "link_flair_background_color": "", "link_flair_richtext": [], "link_flair_text_color": "dark", "link_flair_type": "text", "locked": false, "media_only": false, "no_follow": true, "num_comments": 1, "num_crossposts": 0, "over_18": false, "parent_whitelist_status": "no_ads", "permalink": "/r/depression/comments/9slpyz/feels_like_a_fake/", "pinned": false, "pwls": 0, "retrieved_on": 1540884867, "score": 1, "selftext": "Slither of futile hope that telling myself I could do it, maybe my life wasn't such a failure. I'm a failed student, my GPA is shit because I failed to cope with depression and social anxiety, but at times I feel like maybe it isn't that bad.. So I get out of my messy bed and took a shower.\n\nI feel slightly better when I'm in contact with people but that's just reminds me after we separate that I'm a fucking failure in life. This state of not truly having a breakdown but empty inside makes me feel like a fake.\n\nMaybe I'm not depressed, maybe I don't have social anxiety, maybe it's all made up for an excuse of wasted space that I am.", "send_replies": true, "spoiler": false, "stickied": false, "subreddit": "depression", "subreddit_id": "t5_2qqqf", "subreddit_subscribers": 400486, "subreddit_type": "public", "suggested_sort": "confidence", "thumbnail": "self", "title": "Feels like a fake", "url": "https://www.reddit.com/r/depression/comments/9slpyz/feels_like_a_fake/", "whitelist_status": "no_ads", "wls": 0}, {"author": "zzzzkhi", "author_flair_css_class": null, "author_flair_richtext": [], "author_flair_text": null, "author_flair_type": "text", "author_fullname": "t2_1k1bfsqq", "author_patreon_flair": false, "can_mod_post": false, "contest_mode": false, "created_utc": 1540818554, "domain": "self.depression", "full_link": "https://www.reddit.com/r/depression/comments/9scxdw/how_to_be_self_motivated/", "gildings": {"gid_1": 0, "gid_2": 0, "gid_3": 0}, "id": "9scxdw", "is_crosspostable": true, "is_meta": false, "is_original_content": false, "is_reddit_media_domain": false, "is_robot_indexable": true, "is_self": true, "is_video": false, "link_flair_background_color": "", "link_flair_richtext": [], "link_flair_text_color": "dark", "link_flair_type": "text", "locked": false, "media_only": false, "no_follow": true, "num_comments": 4, "num_crossposts": 0, "over_18": false, "parent_whitelist_status": "no_ads", "permalink": "/r/depression/comments/9scxdw/how_to_be_self_motivated/", "pinned": false, "pwls": 0, "retrieved_on": 1540818651, "score": 1, "selftext": "When you don't even care enough for yourself..", "send_replies": true, "spoiler": false, "stickied": false, "subreddit": "depression", "subreddit_id": "t5_2qqqf", "subreddit_subscribers": 400124, "subreddit_type": "public", "suggested_sort": "confidence", "thumbnail": "self", "title": "how to be self motivated?", "url": "https://www.reddit.com/r/depression/comments/9scxdw/how_to_be_self_motivated/", "whitelist_status": "no_ads", "wls": 0}, {"author": "zzzzkhi", "author_flair_css_class": null, "author_flair_richtext": [], "author_flair_text": null, "author_flair_type": "text", "author_fullname": "t2_1k1bfsqq", "author_patreon_flair": false, "can_mod_post": false, "contest_mode": false, "created_utc": 1540817918, "domain": "self.Trufemcels", "full_link": "https://www.reddit.com/r/Trufemcels/comments/9scu9x/what_do_you_think_about_this_story_trope/", "gildings": {"gid_1": 0, "gid_2": 0, "gid_3": 0}, "id": "9scu9x", "is_crosspostable": true, "is_meta": false, "is_original_content": false, "is_reddit_media_domain": false, "is_robot_indexable": true, "is_self": true, "is_video": false, "link_flair_background_color": "", "link_flair_richtext": [], "link_flair_text_color": "dark", "link_flair_type": "text", "locked": false, "media_only": false, "no_follow": true, "num_comments": 12, "num_crossposts": 0, "over_18": false, "permalink": "/r/Trufemcels/comments/9scu9x/what_do_you_think_about_this_story_trope/", "pinned": false, "retrieved_on": 1540817920, "score": 1, "selftext": "About usually a girl trying to \"fix\" broken guy..\nOr generally this idea that (usually from a guys point of view) having a partner or a lover would make you happier, lift your depression etc.\n\nAnyhow if mod wants me to move this to the ask sub, just say so", "send_replies": true, "spoiler": false, "stickied": false, "subreddit": "Trufemcels", "subreddit_id": "t5_hnz41", "subreddit_subscribers": 5403, "subreddit_type": "public", "thumbnail": "self", "title": "What do you think about this story trope?", "url": "https://www.reddit.com/r/Trufemcels/comments/9scu9x/what_do_you_think_about_this_story_trope/"}, {"author": "zzzzkhi", "author_flair_css_class": null, "author_flair_richtext": [], "author_flair_text": null, "author_flair_type": "text", "author_fullname": "t2_1k1bfsqq", "author_patreon_flair": false, "can_mod_post": false, "contest_mode": false, "created_utc": 1540801099, "domain": "self.Trufemcels", "full_link": "https://www.reddit.com/r/Trufemcels/comments/9sb87u/advice_on_careermaxxing/", "gildings": {"gid_1": 0, "gid_2": 0, "gid_3": 0}, "id": "9sb87u", "is_crosspostable": true, "is_meta": false, "is_original_content": false, "is_reddit_media_domain": false, "is_robot_indexable": true, "is_self": true, "is_video": false, "link_flair_background_color": "", "link_flair_richtext": [], "link_flair_text_color": "dark", "link_flair_type": "text", "locked": false, "media_only": false, "no_follow": true, "num_comments": 6, "num_crossposts": 0, "over_18": false, "permalink": "/r/Trufemcels/comments/9sb87u/advice_on_careermaxxing/", "pinned": false, "retrieved_on": 1540801100, "score": 1, "selftext": "Might be too broad of a context, but I'm asking because I'm socially inept and have social anxiety..", "send_replies": true, "spoiler": false, "stickied": false, "subreddit": "Trufemcels", "subreddit_id": "t5_hnz41", "subreddit_subscribers": 5395, "subreddit_type": "public", "thumbnail": "self", "title": "Advice on careermaxxing?", "url": "https://www.reddit.com/r/Trufemcels/comments/9sb87u/advice_on_careermaxxing/"}, {"author": "zzzzkhi", "author_flair_css_class": null, "author_flair_richtext": [], "author_flair_text": null, "author_flair_type": "text", "author_fullname": "t2_1k1bfsqq", "author_patreon_flair": false, "can_mod_post": false, "contest_mode": false, "created_utc": 1540389456, "domain": "self.depression", "full_link": "https://www.reddit.com/r/depression/comments/9qzwb6/wanting_to_pause_life/", "gildings": {"gid_1": 0, "gid_2": 0, "gid_3": 0}, "id": "9qzwb6", "is_crosspostable": true, "is_meta": false, "is_original_content": false, "is_reddit_media_domain": false, "is_robot_indexable": true, "is_self": true, "is_video": false, "link_flair_background_color": "", "link_flair_richtext": [], "link_flair_text_color": "dark", "link_flair_type": "text", "locked": false, "media_only": false, "no_follow": true, "num_comments": 3, "num_crossposts": 0, "over_18": false, "parent_whitelist_status": "all_ads", "permalink": "/r/depression/comments/9qzwb6/wanting_to_pause_life/", "pinned": false, "pwls": 6, "retrieved_on": 1540389458, "score": 1, "selftext": "I wanna vent, idc if everybody ignored this because it's my problem. \n\ntldr if you need a break  from  life, take it don't be shameful of it..\n\n.\n\nso I spend my life mostly in school, I was in accelerated program 3 times so I got into college when I was 15 (considered rly young in my country). It should be fine if I had an emotional support system, I don't. \n\nmy mom is emotionally abusive, wants me to become a certain type of people (esp wants me to become religious), compared me a lot to my sis or other relatives. my dad works overseas and my sis is well, we aren't close. I had no close friends, acquaintances are many but I cant open up to them. I never took holidays; the travels I had are the ones my mom insist on wanting (usually to relatives place etc). I don't like birthdays or personal party either, I don't think I deserves any of that. I  was  bullied  in  junior  high, but  I  endured it  well  enough  to  graduate  with  a  good  enough  scores  and  I  had  friends  back  then. High  school  is  literal  drag, everyday  was  a  chore  and  I  had  the  same  people Ive  gone  to  junior  high  w.. I  wasn't bullied  but  ignored  for  most  of  the  time. Friends  at  this  time  didn't last  long  and  I  don't  get  to  draw  (my  only  hobby  tbh) because  the  need  to  study , study, study.\n\nAnyhow life was fucking boring, tiring, slowly but surely I developed social anxiety to a degree. I'm fine with strangers, crowded public places, but I have problem dealing with staff in college. Im scared of desk staff, I'm scared to talk anything college related to them unless I'm with someone. I'm scared of places I've problem with. And it fucked me up.\n\nI sometimes cry when people are their happiest, I was crying when my sister graduate  college. I didn't get it myself but I was upset to the point I annoyed my dad. maybe at that point I was depressed about life. Maybe I was always have dysthymia\n\nNothing but the distractions were good. anyhow college is a fucking wreck. Mediocre score everything. And I realized I like drawing better than my current major and I indulged in it. Until the anhedonia hits. I draw and draw like pushing out all of my life force and when it ends, nothing. It felt as empty as I started.\n\nI wanted to take a break but I cant bring it up to my parents and there I am wasting 2 fucking years. take  it  for  granted  I'll graduate  one  year  late  anyway  but  the  other  one  year  is  just  wasted. 1 year.\n\n1 years of doing nothing  but  being  depressed.\nAnd  I  stupidly  still  paid  the  fucking  tuition because  my  parents  don't  want  me  to  delay  it  any  longer. But  I  cant. I  cant  fucking  handle  going  to  my  college  at  that  time  because  it  haunts  me, I'm still  scared  of  those staff counters  and  my  teachers. It  took  me  three  whole  months  to  ask  about  something  trivial. I  stopped  going  to  therapy  because  my  family  opposed  to  it  and  I'm  by  default  just  laid  back  and  said  yes  i  don't  need  it  in  my  head.\n\nMy  sis  is the most understanding so far but asked  if  I  had \"enough  break\"\n\nDo  you  think  I  don't  have  guilt  over  how  expensive  the  cost  of  the wasted tuition  is?\n\nDo  you  think  I  enjoyed  those  ONE  YEAR  OF  NOTHINGNESS\n\ndo  you  think  I  love  having  social  anxiety  and  just  being stressed over  talking  to  people  IRL\n\nno  I  fucking  dont\n\nI'm tired\nIm  tired  of  life\n\nI  want  to  crash  and  burn  somewhere, drown  and  disappear\nI know I was being irrational, I know. I know most people don't have ill intentions. But it's still breaks me down.\n\nIk some of you probably thinks I'm privileged shits but fuck, yes do replace me. I'm sure literally anyone would be better at handling life than me. ", "send_replies": true, "spoiler": false, "stickied": false, "subreddit": "depression", "subreddit_id": "t5_2qqqf", "subreddit_subscribers": 398721, "subreddit_type": "public", "suggested_sort": "confidence", "thumbnail": "self", "title": "Wanting to pause life", "url": "https://www.reddit.com/r/depression/comments/9qzwb6/wanting_to_pause_life/", "whitelist_status": "all_ads", "wls": 6}, {"author": "zzzzkhi", "author_flair_css_class": null, "author_flair_richtext": [], "author_flair_text": null, "author_flair_type": "text", "author_fullname": "t2_1k1bfsqq", "author_patreon_flair": false, "can_mod_post": false, "contest_mode": false, "created_utc": 1540258780, "domain": "self.depression", "full_link": "https://www.reddit.com/r/depression/comments/9qkb96/dont_you_have_friends/", "gildings": {"gid_1": 0, "gid_2": 0, "gid_3": 0}, "id": "9qkb96", "is_crosspostable": true, "is_meta": false, "is_original_content": false, "is_reddit_media_domain": false, "is_robot_indexable": true, "is_self": true, "is_video": false, "link_flair_background_color": "", "link_flair_richtext": [], "link_flair_text_color": "dark", "link_flair_type": "text", "locked": false, "media_only": false, "no_follow": true, "num_comments": 15, "num_crossposts": 0, "over_18": false, "parent_whitelist_status": "all_ads", "permalink": "/r/depression/comments/9qkb96/dont_you_have_friends/", "pinned": false, "pwls": 6, "retrieved_on": 1540258781, "score": 1, "selftext": "I literally feel like I've been hit by a brick every time this phrase comes out. From teachers, families, therapist etc.\n\nI don't, at least the one I'm comfortable to ask around without being gullible or thinking I'm being too clingy. Saying I don't have friends IRL sounds miserable af and I don't want to be miserable. I don't need pity. It's tiring. ", "send_replies": true, "spoiler": false, "stickied": false, "subreddit": "depression", "subreddit_id": "t5_2qqqf", "subreddit_subscribers": 398498, "subreddit_type": "public", "suggested_sort": "confidence", "thumbnail": "self", "title": "\"don't you have friends?\"", "url": "https://www.reddit.com/r/depression/comments/9qkb96/dont_you_have_friends/", "whitelist_status": "all_ads", "wls": 6}, {"author": "zzzzkhi", "author_flair_css_class": null, "author_flair_richtext": [], "author_flair_text": null, "author_flair_type": "text", "author_fullname": "t2_1k1bfsqq", "author_patreon_flair": false, "can_mod_post": false, "contest_mode": false, "created_utc": 1540249268, "domain": "self.depression", "full_link": "https://www.reddit.com/r/depression/comments/9qj1be/afraid_to_involve_other_people/", "gildings": {"gid_1": 0, "gid_2": 0, "gid_3": 0}, "id": "9qj1be", "is_crosspostable": true, "is_meta": false, "is_original_content": false, "is_reddit_media_domain": false, "is_robot_indexable": true, "is_self": true, "is_video": false, "link_flair_background_color": "", "link_flair_richtext": [], "link_flair_text_color": "dark", "link_flair_type": "text", "locked": false, "media_only": false, "no_follow": true, "num_comments": 2, "num_crossposts": 0, "over_18": false, "parent_whitelist_status": "all_ads", "permalink": "/r/depression/comments/9qj1be/afraid_to_involve_other_people/", "pinned": false, "pwls": 6, "retrieved_on": 1540249270, "score": 1, "selftext": "This is highly specific, but I just realized why I delayed my graduation paper too late--like two year late. I don't have problem writing it but I've problem presenting it.\n\nThe thought of presenting it in front of friends or batch mates, no matter how small of the audience it is. I hate it. It makes my stomach churns. Thus it makes me more depressed not starting my paper and now planning to graduate far far too late after the fact. Is this a thing? Or I'm just exaggerating small problem.\n\nI really hate talking to authoritative figures in my college too, like academic staff. Their counter always intimidates me. Idk whats wrong with me because outside of this loop, I'm okay with normal casual interactions to a certain extend. I'm okay with public places but at college I feel like I'm being judged no matter what I do. ", "send_replies": true, "spoiler": false, "stickied": false, "subreddit": "depression", "subreddit_id": "t5_2qqqf", "subreddit_subscribers": 398442, "subreddit_type": "public", "suggested_sort": "confidence", "thumbnail": "self", "title": "Afraid to involve other people", "url": "https://www.reddit.com/r/depression/comments/9qj1be/afraid_to_involve_other_people/", "whitelist_status": "all_ads", "wls": 6}, {"author": "zzzzkhi", "author_flair_css_class": null, "author_flair_richtext": [], "author_flair_text": null, "author_flair_type": "text", "author_fullname": "t2_1k1bfsqq", "can_mod_post": false, "contest_mode": false, "created_utc": 1538850655, "domain": "self.Trufemcels", "full_link": "https://www.reddit.com/r/Trufemcels/comments/9ly9ew/vent_i_know_this_is_petty_af_but/", "gildings": {"gid_1": 0, "gid_2": 0, "gid_3": 0}, "id": "9ly9ew", "is_crosspostable": true, "is_meta": false, "is_original_content": false, "is_reddit_media_domain": false, "is_robot_indexable": false, "is_self": true, "is_video": false, "link_flair_background_color": "", "link_flair_richtext": [], "link_flair_text_color": "dark", "link_flair_type": "text", "locked": false, "media_only": false, "no_follow": true, "num_comments": 24, "num_crossposts": 0, "over_18": false, "permalink": "/r/Trufemcels/comments/9ly9ew/vent_i_know_this_is_petty_af_but/", "pinned": false, "retrieved_on": 1538850657, "score": 1, "selftext": "Maybe incels unrelated, but def lookism related \n\nsometimes I'm just really envious at talented people (in this case arts) which by coincidence they also are beautiful/pretty looking person either it's a guy or a girl. idk it made me feel like shit, like wow they really won in both aspects huh\n\nDon't get me wrong, I don't disregard their hard work especially when arts, music, etc takes years of practice to make it perfect. Diamond won't shines unless they're polished.\nBut it's still disheartening, I feel like I lost in all aspects when I saw those post online.", "send_replies": true, "spoiler": false, "stickied": false, "subreddit": "Trufemcels", "subreddit_id": "t5_hnz41", "subreddit_subscribers": 4725, "subreddit_type": "public", "thumbnail": "self", "title": "(vent) i know this is petty af but...", "url": "https://www.reddit.com/r/Trufemcels/comments/9ly9ew/vent_i_know_this_is_petty_af_but/"}, {"author": "zzzzkhi", "author_flair_css_class": null, "author_flair_richtext": [], "author_flair_text": null, "author_flair_type": "text", "author_fullname": "t2_1k1bfsqq", "can_mod_post": false, "contest_mode": false, "created_utc": 1538344027, "domain": "self.bipolar", "full_link": "https://www.reddit.com/r/bipolar/comments/9kac6n/better_mood_nearon_period/", "gildings": {"gid_1": 0, "gid_2": 0, "gid_3": 0}, "id": "9kac6n", "is_crosspostable": true, "is_meta": false, "is_original_content": false, "is_reddit_media_domain": false, "is_self": true, "is_video": false, "link_flair_background_color": "", "link_flair_richtext": [], "link_flair_text_color": "dark", "link_flair_type": "text", "locked": false, "media_only": false, "no_follow": true, "num_comments": 2, "num_crossposts": 0, "over_18": false, "parent_whitelist_status": "all_ads", "permalink": "/r/bipolar/comments/9kac6n/better_mood_nearon_period/", "pinned": false, "pwls": 6, "retrieved_on": 1538344028, "score": 1, "selftext": "recently diagnosed with dysthymia, but I noticed a pattern lately that my mood is better near period (due to hormonal change maybe?)\n\nTo keep it short, idk if it's a manic phase or just normal base level mood. I'm bad at identifying my mood, but while I feel like this I'll try to describe it while it last. I feel oddly urged to do something; showering, cleaning my room, to at least function, I feel restless, at this time around I can actually exercise.. (Idk how long it will last but mid period it will gone to the depressed state again)\n\nDoes anyone have this pattern? I'm not on anti depressant anymore because I'm afraid to go to the therapist again (I ghosted them) ", "send_replies": true, "spoiler": false, "stickied": false, "subreddit": "bipolar", "subreddit_id": "t5_2qnv4", "subreddit_subscribers": 51542, "subreddit_type": "public", "thumbnail": "self", "title": "better mood near/on period?", "url": "https://www.reddit.com/r/bipolar/comments/9kac6n/better_mood_nearon_period/", "whitelist_status": "all_ads", "wls": 6}, {"author": "zzzzkhi", "author_flair_css_class": null, "author_flair_richtext": [], "author_flair_text": null, "author_flair_type": "text", "author_fullname": "t2_1k1bfsqq", "can_mod_post": false, "contest_mode": false, "created_utc": 1538343314, "domain": "self.depression", "full_link": "https://www.reddit.com/r/depression/comments/9ka8w3/better_mood_nearon_period/", "gildings": {"gid_1": 0, "gid_2": 0, "gid_3": 0}, "id": "9ka8w3", "is_crosspostable": true, "is_meta": false, "is_original_content": false, "is_reddit_media_domain": false, "is_self": true, "is_video": false, "link_flair_background_color": "", "link_flair_richtext": [], "link_flair_text_color": "dark", "link_flair_type": "text", "locked": false, "media_only": false, "no_follow": true, "num_comments": 0, "num_crossposts": 0, "over_18": false, "parent_whitelist_status": "all_ads", "permalink": "/r/depression/comments/9ka8w3/better_mood_nearon_period/", "pinned": false, "pwls": 6, "retrieved_on": 1538343315, "score": 1, "selftext": "Hello I've been diagnosed with dysthymia (off med now that I'm anxious to go to the psychiatrist and therapist again  bc  I  ghosted  them) and have had periods (usually 1 week max where I really feel bad/depressed; literally  don't shower, horrible  sleeping  patterns  and  overeating)\n\nI  don't self  harm  but  there's times  that  I  just  cried  because my  brain  just  reminded  me  how  shitty  and  useless  of  a  human  being  I am.\n\nit's been worse especially since last year, but I just noticed around these last two months that my mood is significantly better (like actually feel normal for once and not shitty for existing) near or at my period,  I knew it's probably hormonal and it will down slope like shit after it ends. This  is  a  problem  for  me  because for  a  week  or  so  I  feel  good  enough  to  function but  the  next 3 week  I'm basically human  log.\n\nIs this PMDD (pre  menstural  dysporic  disorder)? Does anyone else here experience this kind of pattern?", "send_replies": true, "spoiler": false, "stickied": false, "subreddit": "depression", "subreddit_id": "t5_2qqqf", "subreddit_subscribers": 391450, "subreddit_type": "public", "suggested_sort": "confidence", "thumbnail": "self", "title": "Better mood near/on period?", "url": "https://www.reddit.com/r/depression/comments/9ka8w3/better_mood_nearon_period/", "whitelist_status": "all_ads", "wls": 6}, {"author": "zzzzkhi", "author_flair_css_class": null, "author_flair_richtext": [], "author_flair_text": null, "author_flair_type": "text", "author_fullname": "t2_1k1bfsqq", "can_mod_post": false, "contest_mode": false, "created_utc": 1538300012, "domain": "i.redd.it", "full_link": "https://www.reddit.com/r/BoneAppleTea/comments/9k51da/legit_cant_fandom_the_fact/", "gildings": {"gid_1": 0, "gid_2": 0, "gid_3": 0}, "id": "9k51da", "is_crosspostable": true, "is_meta": false, "is_original_content": false, "is_reddit_media_domain": true, "is_self": false, "is_video": false, "link_flair_background_color": "", "link_flair_richtext": [], "link_flair_text": "Ledge it", "link_flair_text_color": "dark", "link_flair_type": "text", "locked": false, "media_only": false, "no_follow": true, "num_comments": 0, "num_crossposts": 0, "over_18": false, "permalink": "/r/BoneAppleTea/comments/9k51da/legit_cant_fandom_the_fact/", "pinned": false, "post_hint": "image", "preview": {"enabled": true, "images": [{"id": "XqzdiFsxeNEpKUCPSbYV2-HplnsLhKoWqR4mOmaMwsw", "resolutions": [{"height": 125, "url": "https://preview.redd.it/n0xoz1e7icp11.jpg?width=108&amp;crop=smart&amp;s=4184418e022bcb27a34c1d99e68f6347583e5fbb", "width": 108}, {"height": 250, "url": "https://preview.redd.it/n0xoz1e7icp11.jpg?width=216&amp;crop=smart&amp;s=0b38a36dce880fa380ac8e54b63763a52816a7ef", "width": 216}, {"height": 370, "url": "https://preview.redd.it/n0xoz1e7icp11.jpg?width=320&amp;crop=smart&amp;s=77c700d7d7ce226dd34c162571068f34f3d61d9c", "width": 320}, {"height": 741, "url": "https://preview.redd.it/n0xoz1e7icp11.jpg?width=640&amp;crop=smart&amp;s=4adb975b6a03c6f96ada75501ed88ab84d85c8a9", "width": 640}], "source": {"height": 831, "url": "https://preview.redd.it/n0xoz1e7icp11.jpg?s=aca0790b6a9b6156ae964af65492925486a06ac3", "width": 717}, "variants": {}}]}, "retrieved_on": 1538300013, "score": 1, "selftext": "", "send_replies": true, "spoiler": false, "stickied": false, "subreddit": "BoneAppleTea", "subreddit_id": "t5_3g7ta", "subreddit_subscribers": 185645, "subreddit_type": "public", "thumbnail": "https://a.thumbs.redditmedia.com/jQz7bZOaH05YAyp4dbzPcvUomPszQQxx1WfLYHkM7i0.jpg", "thumbnail_height": 140, "thumbnail_width": 140, "title": "[legit] cant fandom the fact", "url": "https://i.redd.it/n0xoz1e7icp11.jpg"}, {"author": "zzzzkhi", "author_flair_css_class": null, "author_flair_richtext": [], "author_flair_text": null, "author_flair_type": "text", "author_fullname": "t2_1k1bfsqq", "can_mod_post": false, "contest_mode": false, "created_utc": 1537815195, "domain": "self.Trufemcels", "full_link": "https://www.reddit.com/r/Trufemcels/comments/9ikp1e/femcel_in_media/", "gildings": {"gid_1": 0, "gid_2": 0, "gid_3": 0}, "id": "9ikp1e", "is_crosspostable": true, "is_meta": false, "is_original_content": false, "is_reddit_media_domain": false, "is_self": true, "is_video": false, "link_flair_background_color": "", "link_flair_richtext": [], "link_flair_text_color": "dark", "link_flair_type": "text", "locked": false, "media_only": false, "no_follow": true, "num_comments": 23, "num_crossposts": 0, "over_18": false, "permalink": "/r/Trufemcels/comments/9ikp1e/femcel_in_media/", "pinned": false, "retrieved_on": 1537815196, "score": 1, "selftext": "Is there any portrayal of actual femcel (as the MC) in popular media? :/\n\nWhat comes to mind for me are usually those ugly duckling trope but those are a joke because apparently if you put a glasses on a girl, they become ugly.\n\nAnother example would be post plastic surgery story like 200 pounds of beauty or my id is gangnam beauty.\nIdk I just wanted to know what kind of story resonates the most with what people in this sub reddit are struggling with, if you can recommend any please do ^^\n\n((English is not my first language and I type this at 2 am on my phone so yeah sorry if I make any mistakes)) ", "send_replies": true, "spoiler": false, "stickied": false, "subreddit": "Trufemcels", "subreddit_id": "t5_hnz41", "subreddit_subscribers": 4448, "subreddit_type": "public", "thumbnail": "self", "title": "femcel in media", "url": "https://www.reddit.com/r/Trufemcels/comments/9ikp1e/femcel_in_media/"}, {"author": "zzzzkhi", "author_flair_css_class": null, "author_flair_richtext": [], "author_flair_text": null, "author_flair_type": "text", "author_fullname": "t2_1k1bfsqq", "can_mod_post": false, "contest_mode": false, "created_utc": 1537758452, "domain": "self.depression", "full_link": "https://www.reddit.com/r/depression/comments/9ieixj/i_wish_i_had_a_friend_i_can_share_everything_with/", "id": "9ieixj", "is_crosspostable": true, "is_meta": false, "is_original_content": false, "is_reddit_media_domain": false, "is_self": true, "is_video": false, "link_flair_background_color": "", "link_flair_richtext": [], "link_flair_text_color": "dark", "link_flair_type": "text", "locked": false, "media_only": false, "no_follow": true, "num_comments": 10, "num_crossposts": 0, "over_18": false, "parent_whitelist_status": "all_ads", "permalink": "/r/depression/comments/9ieixj/i_wish_i_had_a_friend_i_can_share_everything_with/", "pinned": false, "pwls": 6, "retrieved_on": 1537758453, "score": 1, "selftext": "I know I could do better, I just... I want someone to support me. Maybe not essentially picking me up from a rut but definitely giving me a push.\n\nIt's hard when you barely have any then realised people that you've been with the longest don't care about you at all. I'm tired of being counter dependant and now that I can barely do anything with my life, I'm just tired. I want someone to be here. ", "send_replies": true, "spoiler": false, "stickied": false, "subreddit": "depression", "subreddit_id": "t5_2qqqf", "subreddit_subscribers": 389452, "subreddit_type": "public", "suggested_sort": "confidence", "thumbnail": "self", "title": "I wish i had a friend i can share everything with", "url": "https://www.reddit.com/r/depression/comments/9ieixj/i_wish_i_had_a_friend_i_can_share_everything_with/", "whitelist_status": "all_ads", "wls": 6}, {"author": "zzzzkhi", "author_flair_css_class": null, "author_flair_richtext": [], "author_flair_text": null, "author_flair_type": "text", "author_fullname": "t2_1k1bfsqq", "can_mod_post": false, "contest_mode": false, "created_utc": 1537642164, "domain": "self.depression", "full_link": "https://www.reddit.com/r/depression/comments/9i21wk/does_anyone_felt_like_they_are_crashing/", "id": "9i21wk", "is_crosspostable": true, "is_meta": false, "is_original_content": false, "is_reddit_media_domain": false, "is_self": true, "is_video": false, "link_flair_background_color": "", "link_flair_richtext": [], "link_flair_text_color": "dark", "link_flair_type": "text", "locked": false, "media_only": false, "no_follow": true, "num_comments": 2, "num_crossposts": 0, "over_18": false, "parent_whitelist_status": "all_ads", "permalink": "/r/depression/comments/9i21wk/does_anyone_felt_like_they_are_crashing/", "pinned": false, "pwls": 6, "retrieved_on": 1537642166, "score": 1, "selftext": "Like driving at full speed and doesn't have the steering wheel under your control, like your mind have been numbed by all the momentary excitement you had and then let down again by yourself and life, repeating the cycle.\n\nLike you can't slow everything down, time passes you like an arrow yet you're stuck, no fuel to do anything. No one encourages you to do anything because you're technically adult yet they won't listen to your struggles. I'm tired riding onto this pathetic life, I'd rather stepped on the gas pedal full force and crash. ", "send_replies": true, "spoiler": false, "stickied": false, "subreddit": "depression", "subreddit_id": "t5_2qqqf", "subreddit_subscribers": 388883, "subreddit_type": "public", "suggested_sort": "confidence", "thumbnail": "self", "title": "Does anyone felt like they are crashing", "url": "https://www.reddit.com/r/depression/comments/9i21wk/does_anyone_felt_like_they_are_crashing/", "whitelist_status": "all_ads", "wls": 6}, {"author": "zzzzkhi", "author_flair_css_class": null, "author_flair_richtext": [], "author_flair_text": null, "author_flair_type": "text", "author_fullname": "t2_1k1bfsqq", "can_mod_post": false, "contest_mode": false, "created_utc": 1537639545, "domain": "self.depression", "full_link": "https://www.reddit.com/r/depression/comments/9i1pov/in_a_limbo_of_changes_and_nothing_at_all/", "id": "9i1pov", "is_crosspostable": true, "is_meta": false, "is_original_content": false, "is_reddit_media_domain": false, "is_self": true, "is_video": false, "link_flair_background_color": "", "link_flair_richtext": [], "link_flair_text_color": "dark", "link_flair_type": "text", "locked": false, "media_only": false, "no_follow": true, "num_comments": 0, "num_crossposts": 0, "over_18": false, "parent_whitelist_status": "all_ads", "permalink": "/r/depression/comments/9i1pov/in_a_limbo_of_changes_and_nothing_at_all/", "pinned": false, "pwls": 6, "retrieved_on": 1537639545, "score": 1, "selftext": "I hate how you can't snapped out of bad habit, I'm 20 and it's been going down hill since I entered college at 15. I can't tell I wanted to stop but changing myself for the better is hard.\n\nI would stop trying, exercising and when it comes to worse not showering, over eats and having breakdowns like a fucking crybaby. I hate that the only time I felt slightly better is when my period comes because it cause mood swings, I hate being dysthymia and dejected about life but there's no one to support me in the end. ", "send_replies": true, "spoiler": false, "stickied": false, "subreddit": "depression", "subreddit_id": "t5_2qqqf", "subreddit_subscribers": 388882, "subreddit_type": "public", "suggested_sort": "confidence", "thumbnail": "self", "title": "In a limbo of changes and nothing at all", "url": "https://www.reddit.com/r/depression/comments/9i1pov/in_a_limbo_of_changes_and_nothing_at_all/", "whitelist_status": "all_ads", "wls": 6}, {"author": "zzzzkhi", "author_flair_css_class": null, "author_flair_richtext": [], "author_flair_text": null, "author_flair_type": "text", "author_fullname": "t2_1k1bfsqq", "can_mod_post": false, "contest_mode": false, "created_utc": 1537403491, "domain": "self.CPTSD", "full_link": "https://www.reddit.com/r/CPTSD/comments/9hanbf/is_this_childhood_emotional_neglect/", "id": "9hanbf", "is_crosspostable": true, "is_meta": false, "is_original_content": false, "is_reddit_media_domain": false, "is_self": true, "is_video": false, "link_flair_background_color": "", "link_flair_richtext": [], "link_flair_text_color": "dark", "link_flair_type": "text", "locked": false, "media_only": false, "no_follow": true, "num_comments": 4, "num_crossposts": 0, "over_18": false, "parent_whitelist_status": "all_ads", "permalink": "/r/CPTSD/comments/9hanbf/is_this_childhood_emotional_neglect/", "pinned": false, "pwls": 6, "retrieved_on": 1537403492, "score": 1, "selftext": "First of all, I don't like saying what happened to me was abuse- it just felt wrong and I know there's people that suffers much much greater than what Ive gone through. \n\nI don't know if this is the correct sub reddit for childhood emotional neglect, but I saw this is the only sub reddit with post about it. Honestly when I discovered the term it instantly click with me, this gonna be long so bear with me.\n\nThank  you  in  advance if you are bothering to read my ramble.\n\nI'm 20. My dad works over seas, he come back home every 6 months or once a year. My mom is a 7am-5pm worker (teacher), my sister is 8 years older than me. Let's just say I'm just used to being alone since childhood, I remember crying pretty melancholically for no reason when I was a kid, I just feel lonely but I wont admit it.\n\nI  don't remember much  from  my  childhood but I've been really shy and awkward. I remember always having extremely low self esteem. Inexplicably since around elementary I just turnt to dislike things like hugs, anything too close for comfort, I never like celebrating birthdays. I don't like asking too much of my parent; i.e asking for clothes.. I have few friends i hold dear since elementary, but due to next reason we rarely even talks.\n\nAnyway probably my biggest problem was jumping classes/acceleration classes. I was in the program for all three mandatory school (elementary-junior-high) so i cut off three years from the usual 12 years education system. Didn't mean i excel in school, it just happened, i only study for the final graduation exam. I was bullied/ignored in junior and since there was some ex classmate, high school was even more of a chore. I talk less and less with my friends fron elementary, they never reach out so i dont either. I dont like being clingy to someone.\n\nI never joined any school activities (like clubs) mostly because i think anything wouldn't \"suit\" me. I hate when my parents bragging about how \"smart\" i am because i know im not that smart, they never thought me seriously about anything as basic necessities. Most of my school years was just cram schools i didnt take seriously. I started locking myself up more often around this time.\n\nI'm pretty naive and easily influented so when around the time it's near graduation, they coerced me to go for STEM field esp medical. I didn't even feel happy or proud when i got accepted, it just there, happened.\n\nI don't hate them, i know its all my fault. They just often assumes what i want. Often my dad bought me bags etc without asking, whatever, but probably the biggest thing was when i entered college he just went and bought me a laptop without asking me. It's a good laptop but i don't know how to react. They just assumes it would make me \"happy\" it isnt, im happy for it but it isnt what i need.\nI need them to give me a push, something encouraging without comparing me to others. I hate that they probably didnt mean anything bad.\n\nIdk what the term, but i feel like they never letting me making the choices, taken my interests into account. \n\nSince last year, my mental health has been deteriorating badly. I'm just not ready to graduate ,i feel like ill fail as a doctor, or even something lesser, i am subconciously scared to started my paper and making appointments with the professor etc. I lock myself, denying calls from my dad, distracting myself with literally anything.\n\nI don't know who to talk to, i cant talk with my friends i fear they will judge me behind their backs, even my first psychiatrist look bored hearing me. I don't go to the therapy since\n\nHonestly my parents prolly dont need me around, they have my older sister already successful and married.", "send_replies": true, "spoiler": false, "stickied": false, "subreddit": "CPTSD", "subreddit_id": "t5_2vvid", "subreddit_subscribers": 13755, "subreddit_type": "public", "thumbnail": "self", "title": "is this Childhood emotional neglect?", "url": "https://www.reddit.com/r/CPTSD/comments/9hanbf/is_this_childhood_emotional_neglect/", "whitelist_status": "all_ads", "wls": 6}, {"author": "zzzzkhi", "author_flair_css_class": null, "author_flair_richtext": [], "author_flair_text": null, "author_flair_type": "text", "author_fullname": "t2_1k1bfsqq", "can_mod_post": false, "contest_mode": false, "created_utc": 1535924802, "domain": "self.depression", "full_link": "https://www.reddit.com/r/depression/comments/9cfu07/last_resort/", "id": "9cfu07", "is_crosspostable": true, "is_meta": false, "is_original_content": false, "is_reddit_media_domain": false, "is_self": true, "is_video": false, "link_flair_background_color": "", "link_flair_richtext": [], "link_flair_text_color": "dark", "link_flair_type": "text", "locked": false, "media_only": false, "no_follow": true, "num_comments": 2, "num_crossposts": 0, "over_18": false, "parent_whitelist_status": "all_ads", "permalink": "/r/depression/comments/9cfu07/last_resort/", "pinned": false, "pwls": 6, "retrieved_on": 1535924803, "score": 1, "selftext": "(20F) It's not for now, at least I wanna try fixing things I could probably fix and actually continuing to take medicine so my dysthymia didn't relapse into double depression etc etc\n\nBut IF it's all futile, maybe in 5 years, if nothing has changed. I want to commit suicide in the manner that make my family thinks I'm just missing, I hate the thought of them having to carry the shame of having me killing myself. I wanna dispose all paper and things related to me, all kinds of accounts, etc and when it's all done go off somewhere I can go die quietly. I  know  it's easy  to  say  these  thing  but  I  just  want  to  disappear.\n\nI just want to disappear so people forget i even existed. Sorry for the ramble. ", "send_replies": true, "spoiler": false, "stickied": false, "subreddit": "depression", "subreddit_id": "t5_2qqqf", "subreddit_subscribers": 383569, "subreddit_type": "public", "suggested_sort": "confidence", "thumbnail": "self", "title": "last resort", "url": "https://www.reddit.com/r/depression/comments/9cfu07/last_resort/", "whitelist_status": "all_ads", "wls": 6}, {"author": "zzzzkhi", "author_flair_css_class": null, "author_flair_richtext": [], "author_flair_text": null, "author_flair_type": "text", "can_mod_post": false, "contest_mode": false, "created_utc": 1534780907, "domain": "self.wowthanksimcured", "full_link": "https://www.reddit.com/r/wowthanksimcured/comments/98uuj8/just_exorcist_the_demon_that_cause_depression/", "id": "98uuj8", "is_crosspostable": true, "is_meta": false, "is_original_content": false, "is_reddit_media_domain": false, "is_self": true, "is_video": false, "link_flair_background_color": "", "link_flair_richtext": [], "link_flair_text_color": "dark", "link_flair_type": "text", "locked": false, "media_only": false, "no_follow": true, "num_comments": 0, "num_crossposts": 0, "over_18": false, "permalink": "/r/wowthanksimcured/comments/98uuj8/just_exorcist_the_demon_that_cause_depression/", "pinned": false, "retrieved_on": 1534780908, "score": 1, "selftext": "this was over a one month ago after I just got diagnosed with depression and my mom has a wonderful idea to call an uncle that's equivalent of a priest tell me I should get exorcised. Ofc I tell him no and stay in my room for whole two days. I overheard over phone that there's demon or some shit in form of catfish in my room or smth which is a joke bc I have been like this for long but it got worse for last 1-2 years.\n\nAlso  they  tried  to  have  my  older  cousin  w  bipolar exorcised  too, how  fun :D\n\n(note: I'm not Christian and the education of mental illness is pretty much non existent  in  my  country) \n\ntldr family tried to exorcise my depression away, didn't work ofc", "send_replies": true, "spoiler": false, "stickied": false, "subreddit": "wowthanksimcured", "subreddit_id": "t5_3n89k", "subreddit_subscribers": 92360, "subreddit_type": "public", "suggested_sort": "confidence", "thumbnail": "self", "title": "just exorcist the demon that cause depression they said, it would help they said :D", "url": "https://www.reddit.com/r/wowthanksimcured/comments/98uuj8/just_exorcist_the_demon_that_cause_depression/"}, {"author": "zzzzkhi", "author_flair_css_class": null, "author_flair_richtext": [], "author_flair_text": null, "author_flair_type": "text", "can_mod_post": false, "contest_mode": false, "created_utc": 1529947636, "domain": "self.bipolar", "full_link": "https://www.reddit.com/r/bipolar/comments/8tsdvu/my_cousin_has_bipolar_but_families_keep_talking/", "id": "8tsdvu", "is_crosspostable": false, "is_original_content": false, "is_reddit_media_domain": false, "is_self": true, "is_video": false, "link_flair_richtext": [], "link_flair_text_color": "dark", "link_flair_type": "text", "locked": false, "media_only": false, "no_follow": true, "num_comments": 0, "num_crossposts": 0, "over_18": false, "parent_whitelist_status": "all_ads", "permalink": "/r/bipolar/comments/8tsdvu/my_cousin_has_bipolar_but_families_keep_talking/", "pinned": false, "pwls": 6, "retrieved_on": 1529947638, "rte_mode": "markdown", "score": 1, "selftext": "[removed]", "send_replies": true, "spoiler": false, "stickied": false, "subreddit": "bipolar", "subreddit_id": "t5_2qnv4", "subreddit_subscribers": 44138, "subreddit_type": "public", "thumbnail": "self", "title": "My cousin has bipolar but families keep talking about it might be a curse", "url": "https://www.reddit.com/r/bipolar/comments/8tsdvu/my_cousin_has_bipolar_but_families_keep_talking/", "whitelist_status": "all_ads", "wls": 6}, {"author": "zzzzkhi", "author_flair_css_class": null, "author_flair_richtext": [], "author_flair_text": null, "author_flair_type": "text", "can_mod_post": false, "contest_mode": false, "created_utc": 1529903604, "domain": "self.depression", "full_link": "https://www.reddit.com/r/depression/comments/8tny3k/college_and_depression/", "id": "8tny3k", "is_crosspostable": true, "is_original_content": false, "is_reddit_media_domain": false, "is_self": true, "is_video": false, "link_flair_richtext": [], "link_flair_text_color": "dark", "link_flair_type": "text", "locked": false, "media_only": false, "no_follow": true, "num_comments": 3, "num_crossposts": 0, "over_18": false, "parent_whitelist_status": "all_ads", "permalink": "/r/depression/comments/8tny3k/college_and_depression/", "pinned": false, "pwls": 6, "retrieved_on": 1529903605, "rte_mode": "markdown", "score": 1, "selftext": "Hi by the title alone probably this is just your classic depressed college student and I know I fucked up aLOT. But if anyone bothers to read this or ridiculing me for it idc I need this out so I have courage to talk to the university staff. \n\nLong story short I entered university when I am 15; just realized now I suffered / effected by Childhood Emotional Neglect which cause my dysthymia and later on might be double depression. I got enrolled into medical course (ironic I know) and near supposed graduating time I feel heavily pressured and not ready at all to continue on. I get this feeling a lot but idk which way to point; and at times I can not go out from my room for a week, I started having suicidal ideation last year.\n\nThe thing I fucked up the most is my graduation paper, I'm severely antsy about the thought of giving presentation and contacting the lecturer for paper title etc. I got touch with a lecturer but I feel inadequate unless I finished my proposal fully and which I did but 3-4 months late. I have been avoiding meeting with anyone since, I often cut off contact from my family. \n\nI finally got a therapist 4 days ago and diagnosed with dysthymia (which I think is incomplete, honestly the session with the psychiatrist was short af).\n\nI am 5 years into the course because stupid me didn't take a time off needed and focus on my mental health first (I often don't think I even have MDD despite having suicidal ideation and severe lost of interest on my hobbies at the time) ----honestly idk if I can still even finish the course. I'm afraid they would just call BS on my claims, honestly it's easier for me to dropping out and die off somewhere but I don't have enough guts to do that to my parents.\n\nI know it's my fault in the first place, I hate being unmotivated piece of shit stain too. Why I'm even being born at all. ", "send_replies": true, "spoiler": false, "stickied": false, "subreddit": "depression", "subreddit_id": "t5_2qqqf", "subreddit_subscribers": 364044, "subreddit_type": "public", "suggested_sort": "confidence", "thumbnail": "self", "title": "college and depression", "url": "https://www.reddit.com/r/depression/comments/8tny3k/college_and_depression/", "whitelist_status": "all_ads", "wls": 6}, {"author": "zzzzkhi", "author_flair_css_class": null, "author_flair_richtext": [], "author_flair_text": null, "author_flair_type": "text", "can_mod_post": false, "contest_mode": false, "created_utc": 1529640825, "domain": "self.AvPD", "full_link": "https://www.reddit.com/r/AvPD/comments/8syfbd/avoidant_tendencies_and_self_esteem_issues/", "id": "8syfbd", "is_crosspostable": true, "is_original_content": false, "is_reddit_media_domain": false, "is_self": true, "is_video": false, "link_flair_richtext": [], "link_flair_text_color": "dark", "link_flair_type": "text", "locked": false, "media_only": false, "no_follow": true, "num_comments": 6, "num_crossposts": 0, "over_18": false, "permalink": "/r/AvPD/comments/8syfbd/avoidant_tendencies_and_self_esteem_issues/", "pinned": false, "retrieved_on": 1529640825, "rte_mode": "markdown", "score": 1, "selftext": "I have avoidant tendencies and just got diagnosed with dysthymia yesterday, I don't know yet if I do have avpd or not. But I've been avoiding to meet with my lecturers at college and people in general excluding some friends that doesn't know my situation.\n\nI'm mustering up courage to go to the campus today and trying to talk to the head faculty, honestly idk what I'm doing for the past years being such big idiot. I feel like I want to disappear if they kicked me out of college bc of this hh", "send_replies": true, "spoiler": false, "stickied": false, "subreddit": "AvPD", "subreddit_id": "t5_2vjua", "subreddit_subscribers": 5211, "subreddit_type": "public", "thumbnail": "self", "title": "Avoidant tendencies and self esteem issues", "url": "https://www.reddit.com/r/AvPD/comments/8syfbd/avoidant_tendencies_and_self_esteem_issues/"}, {"author": "zzzzkhi", "author_flair_css_class": null, "author_flair_richtext": [], "author_flair_text": null, "author_flair_type": "text", "can_mod_post": false, "contest_mode": false, "created_utc": 1529633343, "domain": "self.dysthymia", "full_link": "https://www.reddit.com/r/dysthymia/comments/8sxnnm/just_got_diagnosed_with_dysthymia_but_i_self/", "id": "8sxnnm", "is_crosspostable": true, "is_original_content": false, "is_reddit_media_domain": false, "is_self": true, "is_video": false, "link_flair_richtext": [], "link_flair_text_color": "dark", "link_flair_type": "text", "locked": false, "media_only": false, "no_follow": true, "num_comments": 5, "num_crossposts": 0, "over_18": false, "permalink": "/r/dysthymia/comments/8sxnnm/just_got_diagnosed_with_dysthymia_but_i_self/", "pinned": false, "retrieved_on": 1529633343, "rte_mode": "markdown", "score": 1, "selftext": "Because I can still feel temporary fun with friends or when I watch a series I enjoy. Especially the former, I get unusually over excited over a small hangout.\n\n I'd have suicidal ideation since last year and feel empty most of the time tho, I don't get myself", "send_replies": true, "spoiler": false, "stickied": false, "subreddit": "dysthymia", "subreddit_id": "t5_2srfv", "subreddit_subscribers": 1301, "subreddit_type": "public", "thumbnail": "self", "title": "Just got diagnosed with dysthymia but i self doubting it", "url": "https://www.reddit.com/r/dysthymia/comments/8sxnnm/just_got_diagnosed_with_dysthymia_but_i_self/"}, {"author": "zzzzkhi", "author_flair_css_class": null, "author_flair_richtext": [], "author_flair_text": null, "author_flair_type": "text", "can_mod_post": false, "contest_mode": false, "created_utc": 1529606139, "domain": "self.depression", "full_link": "https://www.reddit.com/r/depression/comments/8suck7/just_got_diagnosed_with_pdd_dysthymia_anyone_have/", "id": "8suck7", "is_crosspostable": true, "is_original_content": false, "is_reddit_media_domain": false, "is_self": true, "is_video": false, "link_flair_richtext": [], "link_flair_text_color": "dark", "link_flair_type": "text", "locked": false, "media_only": false, "no_follow": true, "num_comments": 1, "num_crossposts": 0, "over_18": false, "parent_whitelist_status": "all_ads", "permalink": "/r/depression/comments/8suck7/just_got_diagnosed_with_pdd_dysthymia_anyone_have/", "pinned": false, "pwls": 6, "retrieved_on": 1529606141, "rte_mode": "markdown", "score": 1, "selftext": "I have been a low energy person especially in my teenage years, often shut in for a period of time. I never truly feel like I live for my own sake and better off disappear. It has exacerbate last years and interfere with my college so much, but I never feel like I am depressed enough to use it as an excuse/getting professional help until now.\n\nThe doctor prescribed me fluoxetine and counselling session with a psychologist.", "send_replies": true, "spoiler": false, "stickied": false, "subreddit": "depression", "subreddit_id": "t5_2qqqf", "subreddit_subscribers": 363005, "subreddit_type": "public", "suggested_sort": "confidence", "thumbnail": "self", "title": "Just got diagnosed with PDD / dysthymia, anyone have experience with this?", "url": "https://www.reddit.com/r/depression/comments/8suck7/just_got_diagnosed_with_pdd_dysthymia_anyone_have/", "whitelist_status": "all_ads", "wls": 6}, {"author": "zzzzkhi", "author_flair_css_class": null, "author_flair_richtext": [], "author_flair_text": null, "author_flair_type": "text", "can_mod_post": false, "contest_mode": false, "created_utc": 1528877477, "domain": "self.depression", "full_link": "https://www.reddit.com/r/depression/comments/8qqqel/i_dont_know/", "id": "8qqqel", "is_crosspostable": true, "is_original_content": false, "is_reddit_media_domain": false, "is_self": true, "is_video": false, "link_flair_richtext": [], "link_flair_text_color": "dark", "link_flair_type": "text", "locked": false, "media_only": false, "no_follow": true, "num_comments": 1, "num_crossposts": 0, "over_18": false, "parent_whitelist_status": "all_ads", "permalink": "/r/depression/comments/8qqqel/i_dont_know/", "pinned": false, "pwls": 6, "retrieved_on": 1528877478, "rte_mode": "markdown", "score": 1, "selftext": "I am on the verge of dropping out (I will see the head of faculty to appeal and extend my study period in two weeks, but  I  doubt  it  will  even  works  due  to  new  government rule  that  limits  the  study  period) but I've been lying about my college progress to my parents. I'm just a worthless piece of shit, why I'm even alive.", "send_replies": true, "spoiler": false, "stickied": false, "subreddit": "depression", "subreddit_id": "t5_2qqqf", "subreddit_subscribers": 360632, "subreddit_type": "public", "suggested_sort": "confidence", "thumbnail": "self", "title": "I dont know", "url": "https://www.reddit.com/r/depression/comments/8qqqel/i_dont_know/", "whitelist_status": "all_ads", "wls": 6}]}